<annotation>
	<folder>data1</folder>
	<filename>30.jpg</filename>
	<path>/home/rishabh/Downloads/data1/30.jpg</path>
	<source>
		<database>Unknown</database>
	</source>
	<size>
		<width>800</width>
		<height>600</height>
		<depth>3</depth>
	</size>
	<segmented>0</segmented>
	<object>
		<name>fixed_amount</name>
		<pose>Unspecified</pose>
		<truncated>0</truncated>
		<difficult>0</difficult>
		<bndbox>
			<xmin>526</xmin>
			<ymin>286</ymin>
			<xmax>620</xmax>
			<ymax>313</ymax>
		</bndbox>
	</object>
	<object>
		<name>create</name>
		<pose>Unspecified</pose>
		<truncated>0</truncated>
		<difficult>0</difficult>
		<bndbox>
			<xmin>63</xmin>
			<ymin>109</ymin>
			<xmax>133</xmax>
			<ymax>131</ymax>
		</bndbox>
	</object>
	<object>
		<name>cc</name>
		<pose>Unspecified</pose>
		<truncated>0</truncated>
		<difficult>0</difficult>
		<bndbox>
			<xmin>574</xmin>
			<ymin>138</ymin>
			<xmax>619</xmax>
			<ymax>160</ymax>
		</bndbox>
	</object>
	<object>
		<name>hyrly</name>
		<pose>Unspecified</pose>
		<truncated>0</truncated>
		<difficult>0</difficult>
		<bndbox>
			<xmin>245</xmin>
			<ymin>281</ymin>
			<xmax>311</xmax>
			<ymax>319</ymax>
		</bndbox>
	</object>
</annotation>
